xrcea/__main__.py
xrcea/components/bbg.comp
xrcea/components/cryp.comp
xrcea/components/describer.comp
xrcea/components/pddb.comp
xrcea/components/bbg/__init__.py
xrcea/components/bbg/polynomial.py
xrcea/components/bbg/splane.py
xrcea/components/cryp/__init__.py
xrcea/components/cryp/broadening.py
xrcea/components/cryp/cellparams.py
xrcea/components/cryp/describer.py
xrcea/components/cryp/fviewer.py
xrcea/components/cryp/indexer.py
xrcea/components/cryp/positions.py
xrcea/components/cryp/preflex.py
xrcea/components/cryp/reflex.py
xrcea/components/cryp/vcellparams.py
xrcea/components/describer/__init__.py
xrcea/components/describer/html.py
xrcea/components/pddb/__init__.py
xrcea/components/pddb/analyse.py
xrcea/components/pddb/browser.py
xrcea/components/pddb/opddb.py
xrcea/components/pddb/pddb.py
xrcea/components/pddb/plot.py
xrcea/core/__init__.py
xrcea/core/application.py
xrcea/core/compman.py
xrcea/core/description.py
xrcea/core/idata.py
xrcea/core/project.py
xrcea/core/sett_dialogs.py
xrcea/core/settings.py
xrcea/core/qt/__init__.py
xrcea/core/qt/core.py
xrcea/core/qt/dialog.py
xrcea/core/qt/idialog.py
xrcea/core/qt/lister.py
xrcea/core/qt/lists.py
xrcea/core/qt/menu.py
xrcea/core/qt/page.py
xrcea/core/qt/plot.py
xrcea/core/qt/progress.py
xrcea/core/qt/spreadsheet.py
xrcea/core/qt/table.py
xrcea/core/qt/text.py
xrcea/core/vi/__init__.py
xrcea/core/vi/lister.py
xrcea/core/vi/menu.py
xrcea/core/vi/mixins.py
xrcea/core/vi/page.py
xrcea/core/vi/plot.py
xrcea/core/vi/spreadsheet.py
xrcea/core/vi/value.py
xrcea/doc/eng/html/core.html
xrcea/doc/eng/html/genindex.html
xrcea/doc/eng/html/index.html
xrcea/doc/eng/html/introduction.html
xrcea/doc/eng/html/objects.inv
xrcea/doc/eng/html/pddb.html
xrcea/doc/eng/html/py-modindex.html
xrcea/doc/eng/html/search.html
xrcea/doc/eng/html/searchindex.js
xrcea/doc/eng/html/xrd_spec.html
xrcea/doc/eng/html/_static/_sphinx_javascript_frameworks_compat.js
xrcea/doc/eng/html/_static/basic.css
xrcea/doc/eng/html/_static/doctools.js
XRCEA-0.2.2.dist-info/LICENSE
XRCEA-0.2.2.dist-info/METADATA
XRCEA-0.2.2.dist-info/WHEEL
XRCEA-0.2.2.dist-info/entry_points.txt
XRCEA-0.2.2.dist-info/top_level.txt
XRCEA-0.2.2.dist-info/RECORD
