Metadata-Version: 2.1
Name: XRCEA
Version: 0.2.2
Summary: X-ray crystallography extensible analyzer
Home-page: https://github.com/Lysovenko/XRCEA
Author: Serhii Lysovenko
Author-email: Lysovenko@users.noreply.github.com
License: GPLv3+
Project-URL: Bug Tracker, https://github.com/Lysovenko/XRCEA/issues
Classifier: Development Status :: 4 - Beta
Classifier: Programming Language :: Python :: 3
Classifier: License :: OSI Approved :: GNU General Public License v3 or later (GPLv3+)
Classifier: Operating System :: OS Independent
Classifier: Environment :: X11 Applications :: Qt
Classifier: Intended Audience :: Science/Research
Classifier: Topic :: Scientific/Engineering :: Physics
Requires-Python: >=3.6
License-File: LICENSE
Requires-Dist: PyQt5
Requires-Dist: matplotlib
Requires-Dist: numpy
Requires-Dist: scipy
